COPYING
MANIFEST.in
README.rst
bootstrap-buildout.py
buildout.cfg
setup.py
docs/conf.py
docs/index.rst
xbob/__init__.py
xbob.db.atvskeystroke.egg-info/PKG-INFO
xbob.db.atvskeystroke.egg-info/SOURCES.txt
xbob.db.atvskeystroke.egg-info/dependency_links.txt
xbob.db.atvskeystroke.egg-info/entry_points.txt
xbob.db.atvskeystroke.egg-info/namespace_packages.txt
xbob.db.atvskeystroke.egg-info/not-zip-safe
xbob.db.atvskeystroke.egg-info/requires.txt
xbob.db.atvskeystroke.egg-info/top_level.txt
xbob/db/__init__.py
xbob/db/atvskeystroke/__init__.py
xbob/db/atvskeystroke/create.py
xbob/db/atvskeystroke/db.sql3
xbob/db/atvskeystroke/driver.py
xbob/db/atvskeystroke/models.py
xbob/db/atvskeystroke/query.py
xbob/db/atvskeystroke/test.py