Metadata-Version: 1.1
Name: xbob.db.atvskeystroke
Version: 0.0.1
Summary: ATVS-Keystroke Database Access API for Bob
Home-page: http://github.com/mgbarrero/xbob.db.atvskeystroke
Author: Marta Gomez-Barrero
Author-email: marta.barrero@uam.es
License: GPLv3
Platform: UNKNOWN
Classifier: Development Status :: 4 - Beta
Classifier: Intended Audience :: Developers
Classifier: License :: OSI Approved :: GNU General Public License v3 (GPLv3)
Classifier: Natural Language :: English
Classifier: Programming Language :: Python
Classifier: Programming Language :: Python :: 3
Classifier: Topic :: Scientific/Engineering :: Artificial Intelligence
Classifier: Topic :: Database :: Front-Ends
